main.py
SimpleVN-0.0.8.dist-info/LICENSE
SimpleVN-0.0.8.dist-info/METADATA
SimpleVN-0.0.8.dist-info/WHEEL
SimpleVN-0.0.8.dist-info/top_level.txt
SimpleVN-0.0.8.dist-info/RECORD
