Metadata-Version: 2.1
Name: SimpleVN
Version: 0.0.8
Summary: A simple module to create really quick visual novels
Home-page: https://github.com/D3REKZHANG/SimpleVN
Author: Menthol - Derek Zhang
Author-email: derek.zhang0210@gmail.com
License: UNKNOWN
Platform: UNKNOWN
Classifier: Programming Language :: Python :: 3
Classifier: License :: OSI Approved :: MIT License
Classifier: Operating System :: OS Independent
